{
  "Rua Floriano Peixoto, 368, Centro, Itapuí - SP": {
    "coords": [
      -22.2327799,
      -48.7181831
    ],
    "timestamp": "2025-08-19T13:37:59.869482"
  },
  "Rafael Regina, 59, Bariri, SP": {
    "coords": [
      -22.0773715,
      -48.7236549
    ],
    "timestamp": "2025-08-19T13:38:05.602215"
  },
  "Domingos Della coletta, 48, Bariri, SP": {
    "coords": [
      -22.0858936,
      -48.7494511
    ],
    "timestamp": "2025-08-19T13:38:11.630421"
  },
  "Fernando bilancieri, 237, Boraceia sp, SP": {
    "coords": [
      -22.1992822,
      -48.7867237
    ],
    "timestamp": "2025-08-19T13:38:17.702829"
  }
}